[
  {
    "id": "task-1766377305081-tqo2hw",
    "planId": "plan-1766377304975",
    "phase": "Setup",
    "name": "Register domain",
    "description": "Acquire domain name",
    "automated": true,
    "requiresApproval": false,
    "estimatedTime": "1 hour",
    "dependencies": [],
    "status": "pending",
    "createdAt": "2025-12-22T04:21:45.081Z"
  },
  {
    "id": "task-1766377305081-hhp29i",
    "planId": "plan-1766377304975",
    "phase": "Setup",
    "name": "Setup branding",
    "description": "Create logo and style",
    "automated": false,
    "requiresApproval": true,
    "approvalReason": "Brand identity review",
    "estimatedTime": "3 hours",
    "dependencies": [],
    "status": "pending",
    "createdAt": "2025-12-22T04:21:45.081Z"
  },
  {
    "id": "task-1766377305081-or9aln",
    "planId": "plan-1766377304975",
    "phase": "Launch",
    "name": "Create landing page",
    "description": "Deploy Vercel site",
    "automated": true,
    "requiresApproval": false,
    "estimatedTime": "2 hours",
    "dependencies": [
      "Register domain"
    ],
    "status": "pending",
    "createdAt": "2025-12-22T04:21:45.081Z"
  },
  {
    "id": "task-1766377305081-1nceau",
    "planId": "plan-1766377304975",
    "phase": "Launch",
    "name": "Cold outreach",
    "description": "Initial sales push",
    "automated": true,
    "requiresApproval": false,
    "estimatedTime": "4 hours",
    "dependencies": [
      "Create landing page"
    ],
    "status": "pending",
    "createdAt": "2025-12-22T04:21:45.081Z"
  }
]